greet2o/__init__.py
greet2o/logic.py
greet2o-0.1.1.dist-info/LICENSE
greet2o-0.1.1.dist-info/METADATA
greet2o-0.1.1.dist-info/WHEEL
greet2o-0.1.1.dist-info/top_level.txt
greet2o-0.1.1.dist-info/RECORD
